CHANGES.txt
DESC.txt
LICENSE.txt
MANIFEST.in
README.md
setup.py
Colr.egg-info/PKG-INFO
Colr.egg-info/SOURCES.txt
Colr.egg-info/dependency_links.txt
Colr.egg-info/entry_points.txt
Colr.egg-info/top_level.txt
colr/__init__.py
colr/__main__.py
colr/base.py
colr/codes.py
colr/colr.py
colr/colr_docopt.py
colr/colr_run.py
colr/colrcontrol.py
colr/control_codes.py
colr/controls.py
colr/name_data.py
colr/preset.py
colr/progress.py
colr/progress_frames.py
colr/trans.py
docs/mit.txt
test/__init__.py
test/last_snippet.py
test/run_colr.py
test/run_controls.py
test/run_progress.py
test/test_base.py
test/test_colr.py
test/test_colr_docopt.py
test/test_colr_tool.py
test/test_colrtestcase.py
test/test_controls.py
test/test_preset.py
test/test_progress.py
test/test_trans.py
test/testing_tools.py