Metadata-Version: 1.1
Name: Colr
Version: 0.9.1
Summary: Easy terminal colors, with chainable methods.
